latte/__init__.py
latte/functional/__init__.py
latte/functional/bundles/__init__.py
latte/functional/bundles/dependency_aware_mutual_info.py
latte/functional/bundles/liad_interpolatability.py
latte/functional/disentanglement/__init__.py
latte/functional/disentanglement/_utils.py
latte/functional/disentanglement/modularity.py
latte/functional/disentanglement/mutual_info.py
latte/functional/disentanglement/sap.py
latte/functional/interpolatability/__init__.py
latte/functional/interpolatability/_utils.py
latte/functional/interpolatability/monotonicity.py
latte/functional/interpolatability/smoothness.py
latte/metrics/__init__.py
latte/metrics/base.py
latte/metrics/core/__init__.py
latte/metrics/core/bundles.py
latte/metrics/core/disentanglement.py
latte/metrics/core/interpolatability.py
latte/metrics/keras/__init__.py
latte/metrics/keras/bundles.py
latte/metrics/keras/disentanglement.py
latte/metrics/keras/interpolatability.py
latte/metrics/keras/wrapper.py
latte/metrics/torch/__init__.py
latte/metrics/torch/bundles.py
latte/metrics/torch/disentanglement.py
latte/metrics/torch/interpolatability.py
latte/metrics/torch/wrapper.py
latte_metrics-0.0.1a6.dist-info/LICENSE
latte_metrics-0.0.1a6.dist-info/METADATA
latte_metrics-0.0.1a6.dist-info/WHEEL
latte_metrics-0.0.1a6.dist-info/top_level.txt
latte_metrics-0.0.1a6.dist-info/RECORD
