Metadata-Version: 2.1
Name: latte-metrics
Version: 0.0.1a6
Summary: Latte: Cross-framework Python Package for Evaluation of Latent-based Generative Models
Home-page: https://github.com/karnwatcharasupat/latte
Author: Karn Watcharasupat
Author-email: karn001@e.ntu.edu.sg
License: MIT
Project-URL: Bug Tracker, https://github.com/karnwatcharasupat/latte/issues
Classifier: License :: OSI Approved :: MIT License
Classifier: Operating System :: OS Independent
Classifier: Programming Language :: Python :: 3
Classifier: Programming Language :: Python :: 3 :: Only
Classifier: Programming Language :: Python :: 3.7
Classifier: Programming Language :: Python :: 3.8
Classifier: Programming Language :: Python :: 3.9
Classifier: Programming Language :: Python :: 3.10
Requires-Python: <3.11,>=3.7
License-File: LICENSE
Requires-Dist: numpy (>=1.18)
Requires-Dist: scikit-learn (>=1.0)
Provides-Extra: all
Requires-Dist: torch (>=1.3.1) ; extra == 'all'
Requires-Dist: torchmetrics (>=0.2) ; extra == 'all'
Requires-Dist: tensorflow (>=2.0) ; extra == 'all'
Provides-Extra: keras
Requires-Dist: tensorflow (>=2.0) ; extra == 'keras'
Provides-Extra: pytorch
Requires-Dist: torch (>=1.3.1) ; extra == 'pytorch'
Requires-Dist: torchmetrics (>=0.2) ; extra == 'pytorch'
Provides-Extra: tests
Requires-Dist: pytest ; extra == 'tests'
Requires-Dist: pytest-cov ; extra == 'tests'
Requires-Dist: pytest-xdist ; extra == 'tests'
